daruma_py2compt/__init__.py
daruma_py2compt/daruma_module.py
daruma_py2compt/functions.py
daruma_py2compt/models.py
daruma_py2compt/data/AAindex553-Normal-X0.feature
daruma_py2compt/data/CNN3_128_9_NN2_121_128.weight
daruma_py2compt-0.0.8.dist-info/METADATA
daruma_py2compt-0.0.8.dist-info/WHEEL
daruma_py2compt-0.0.8.dist-info/entry_points.txt
daruma_py2compt-0.0.8.dist-info/top_level.txt
daruma_py2compt-0.0.8.dist-info/RECORD
